mytextlib/__init__.py
mytextlib/model.py
mytextlib/processing.py
mytextlib/utils.py
tests/__init__.py
tests/test_model.py
mytextlib-0.1.0.dist-info/METADATA
mytextlib-0.1.0.dist-info/WHEEL
mytextlib-0.1.0.dist-info/top_level.txt
mytextlib-0.1.0.dist-info/RECORD
